sharpei/__init__.py
sharpei/cli.py
sharpei/handler.py
sharpei-0.4.0.dist-info/LICENSE
sharpei-0.4.0.dist-info/METADATA
sharpei-0.4.0.dist-info/WHEEL
sharpei-0.4.0.dist-info/entry_points.txt
sharpei-0.4.0.dist-info/top_level.txt
sharpei-0.4.0.dist-info/RECORD
